aliyunsdkimageseg/__init__.py
aliyunsdkimageseg/endpoint.py
aliyunsdkimageseg/request/__init__.py
aliyunsdkimageseg/request/v20191230/ChangeSkyRequest.py
aliyunsdkimageseg/request/v20191230/GetAsyncJobResultRequest.py
aliyunsdkimageseg/request/v20191230/ParseFaceRequest.py
aliyunsdkimageseg/request/v20191230/RefineMaskRequest.py
aliyunsdkimageseg/request/v20191230/SegmentBodyRequest.py
aliyunsdkimageseg/request/v20191230/SegmentClothRequest.py
aliyunsdkimageseg/request/v20191230/SegmentCommodityRequest.py
aliyunsdkimageseg/request/v20191230/SegmentCommonImageRequest.py
aliyunsdkimageseg/request/v20191230/SegmentFoodRequest.py
aliyunsdkimageseg/request/v20191230/SegmentHDBodyRequest.py
aliyunsdkimageseg/request/v20191230/SegmentHDCommonImageRequest.py
aliyunsdkimageseg/request/v20191230/SegmentHDSkyRequest.py
aliyunsdkimageseg/request/v20191230/SegmentHairRequest.py
aliyunsdkimageseg/request/v20191230/SegmentHeadRequest.py
aliyunsdkimageseg/request/v20191230/SegmentSceneRequest.py
aliyunsdkimageseg/request/v20191230/SegmentSkinRequest.py
aliyunsdkimageseg/request/v20191230/SegmentSkyRequest.py
aliyunsdkimageseg/request/v20191230/__init__.py
aliyun_python_sdk_imageseg-1.1.14.dist-info/LICENSE
aliyun_python_sdk_imageseg-1.1.14.dist-info/METADATA
aliyun_python_sdk_imageseg-1.1.14.dist-info/WHEEL
aliyun_python_sdk_imageseg-1.1.14.dist-info/top_level.txt
aliyun_python_sdk_imageseg-1.1.14.dist-info/RECORD
